{"errors":[],"warnings":[],"namedChunkGroups":{"app":{"chunks":[6,0,2],"assets":["webpack-runtime-ae711aff8f745f683a52.js","webpack-runtime-ae711aff8f745f683a52.js.map","commons-d515eac09d1912c42527.js","commons-d515eac09d1912c42527.js.map","app-0a1d2cf6e0775650ddf2.js","app-0a1d2cf6e0775650ddf2.js.map"],"children":{},"childAssets":{}},"component---src-pages-404-js":{"chunks":[1,0,3],"assets":["styles.3fb471d7d3b2e4a63664.css","styles-ecc8a028ce72ffde07fc.js","styles-ecc8a028ce72ffde07fc.js.map","commons-d515eac09d1912c42527.js","commons-d515eac09d1912c42527.js.map","component---src-pages-404-js-afb600133dfed889612a.js","component---src-pages-404-js-afb600133dfed889612a.js.map"],"children":{},"childAssets":{}},"component---src-pages-index-js":{"chunks":[1,0,4],"assets":["styles.3fb471d7d3b2e4a63664.css","styles-ecc8a028ce72ffde07fc.js","styles-ecc8a028ce72ffde07fc.js.map","commons-d515eac09d1912c42527.js","commons-d515eac09d1912c42527.js.map","component---src-pages-index-js-ad476907f513c509015c.js","component---src-pages-index-js-ad476907f513c509015c.js.map"],"children":{},"childAssets":{}},"component---src-pages-page-2-js":{"chunks":[1,0,5],"assets":["styles.3fb471d7d3b2e4a63664.css","styles-ecc8a028ce72ffde07fc.js","styles-ecc8a028ce72ffde07fc.js.map","commons-d515eac09d1912c42527.js","commons-d515eac09d1912c42527.js.map","component---src-pages-page-2-js-3dc2f82252140a4e5722.js","component---src-pages-page-2-js-3dc2f82252140a4e5722.js.map"],"children":{},"childAssets":{}}},"assetsByChunkName":{"app":["webpack-runtime-ae711aff8f745f683a52.js","commons-d515eac09d1912c42527.js","app-0a1d2cf6e0775650ddf2.js"],"component---src-pages-404-js":["styles.3fb471d7d3b2e4a63664.css","styles-ecc8a028ce72ffde07fc.js","commons-d515eac09d1912c42527.js","component---src-pages-404-js-afb600133dfed889612a.js"],"component---src-pages-index-js":["styles.3fb471d7d3b2e4a63664.css","styles-ecc8a028ce72ffde07fc.js","commons-d515eac09d1912c42527.js","component---src-pages-index-js-ad476907f513c509015c.js"],"component---src-pages-page-2-js":["styles.3fb471d7d3b2e4a63664.css","styles-ecc8a028ce72ffde07fc.js","commons-d515eac09d1912c42527.js","component---src-pages-page-2-js-3dc2f82252140a4e5722.js"]}}